dataretrieval/__init__.py
dataretrieval/_version.py
dataretrieval/nadp.py
dataretrieval/nldi.py
dataretrieval/nwis.py
dataretrieval/samples.py
dataretrieval/streamstats.py
dataretrieval/utils.py
dataretrieval/waterwatch.py
dataretrieval/wqp.py
dataretrieval/codes/__init__.py
dataretrieval/codes/states.py
dataretrieval/codes/timezones.py
dataretrieval-1.0.12.dist-info/licenses/LICENSE.md
dataretrieval-1.0.12.dist-info/METADATA
dataretrieval-1.0.12.dist-info/WHEEL
dataretrieval-1.0.12.dist-info/top_level.txt
dataretrieval-1.0.12.dist-info/RECORD
