Metadata-Version: 2.4
Name: dataretrieval
Version: 1.0.12
Summary: Discover and retrieve water data from U.S. federal hydrologic web services.
Author-email: Timothy Hodson <thodson@usgs.gov>
Maintainer-email: Elise Hinman <ehinman@usgs.gov>
License: License
Project-URL: homepage, https://github.com/DOI-USGS/dataretrieval-python
Project-URL: documentation, https://doi-usgs.github.io/dataretrieval-python/
Project-URL: repository, https://github.com/DOI-USGS/dataretrieval-python.git
Keywords: USGS,water data
Classifier: Programming Language :: Python :: 3
Requires-Python: >=3.8
License-File: LICENSE.md
Requires-Dist: requests
Requires-Dist: pandas==2.*
Provides-Extra: test
Requires-Dist: pytest>5.0.0; extra == "test"
Requires-Dist: pytest-cov[all]; extra == "test"
Requires-Dist: coverage; extra == "test"
Requires-Dist: requests-mock; extra == "test"
Requires-Dist: flake8; extra == "test"
Provides-Extra: doc
Requires-Dist: sphinx; extra == "doc"
Requires-Dist: sphinx-rtd-theme; extra == "doc"
Requires-Dist: nbsphinx; extra == "doc"
Requires-Dist: nbsphinx_link; extra == "doc"
Requires-Dist: ipython; extra == "doc"
Requires-Dist: ipykernel; extra == "doc"
Requires-Dist: matplotlib; extra == "doc"
Provides-Extra: nldi
Requires-Dist: geopandas>=0.10; extra == "nldi"
Dynamic: license-file
